CHANGES
LICENSE
MANIFEST.in
README.md
TODO
setup.cfg
setup.py
PyRIC.egg-info/PKG-INFO
PyRIC.egg-info/SOURCES.txt
PyRIC.egg-info/dependency_links.txt
PyRIC.egg-info/top_level.txt
docs/PyRIC.pdf
examples/info.py
examples/pentest.py
pyric/__init__.py
pyric/pyw.py
pyric/lib/__init__.py
pyric/lib/libio.py
pyric/lib/libnl.py
pyric/net/__init__.py
pyric/net/genetlink_h.py
pyric/net/if_h.py
pyric/net/netlink_h.py
pyric/net/policy.py
pyric/net/sockios_h.py
pyric/net/wireless/__init__.py
pyric/net/wireless/nl80211_c.py
pyric/net/wireless/nl80211_h.py
pyric/net/wireless/rfkill_h.py
pyric/net/wireless/wlan.py
pyric/nlhelp/__init__.py
pyric/nlhelp/attributes.help
pyric/nlhelp/commands.help
pyric/nlhelp/nlsearch.py
pyric/utils/__init__.py
pyric/utils/channels.py
pyric/utils/hardware.py
pyric/utils/ouifetch.py
pyric/utils/rfkill.py
pyric/utils/data/oui.txt