Metadata-Version: 1.1
Name: PyRIC
Version: 0.1.6.3
Summary: Python Wireless Library
Home-page: http://wraith-wireless.github.io/PyRIC/
Author: Dale Patterson
Author-email: wraith.wireless@yandex.com
License: GPLv3
Download-URL: https://github.com/wraith-wireless/pyric/archive/0.1.6.3.tar.gz
Keywords: Linux Python nl80211 iw iwconfig ifconfig wireless WLAN WiFi pentest
Platform: UNKNOWN
Classifier: Development Status :: 5 - Production/Stable
Classifier: License :: OSI Approved :: GNU General Public License v3 (GPLv3)
Classifier: Intended Audience :: Developers
Classifier: Intended Audience :: System Administrators
Classifier: Topic :: Security
Classifier: Topic :: Software Development
Classifier: Topic :: Software Development :: Libraries
Classifier: Topic :: Security
Classifier: Topic :: System :: Networking
Classifier: Topic :: Utilities
Classifier: Operating System :: POSIX :: Linux
Classifier: Programming Language :: Python
Classifier: Programming Language :: Python :: 2.7
Classifier: Programming Language :: Python :: 3.0
Classifier: Programming Language :: Python :: 3.5
